frd2vtu/__init__.py
frd2vtu/basic_plot.py
frd2vtu/frd2vtu.py
frd2vtu-0.1.7.dist-info/METADATA
frd2vtu-0.1.7.dist-info/WHEEL
frd2vtu-0.1.7.dist-info/entry_points.txt
frd2vtu-0.1.7.dist-info/licenses/LICENSE
frd2vtu-0.1.7.dist-info/RECORD
