Metadata-Version: 2.4
Name: frd2vtu
Version: 0.1.7
Summary: converter from calculix binary frd to vtu
Author-email: wr1 <8971152+wr1@users.noreply.github.com>
License-Expression: MIT
License-File: LICENSE
Requires-Python: >=3.11
Requires-Dist: numpy>=2.2.6
Requires-Dist: pandas>=2.2.0
Requires-Dist: pyvista==0.44.2
